ovos_skill_hello_world/LICENSE
ovos_skill_hello_world/MANIFEST.in
ovos_skill_hello_world/README.md
ovos_skill_hello_world/__init__.py
ovos_skill_hello_world/requirements.txt
ovos_skill_hello_world/version.py
ovos_skill_hello_world/locale/ca-es/skill.json
ovos_skill_hello_world/locale/ca-es/dialog/hello.dialog
ovos_skill_hello_world/locale/ca-es/dialog/hello.world.dialog
ovos_skill_hello_world/locale/ca-es/dialog/how.are.you.dialog
ovos_skill_hello_world/locale/ca-es/dialog/welcome.dialog
ovos_skill_hello_world/locale/ca-es/intents/Greetings.intent
ovos_skill_hello_world/locale/ca-es/intents/HowAreYou.intent
ovos_skill_hello_world/locale/ca-es/vocab/HelloWorldKeyword.voc
ovos_skill_hello_world/locale/ca-es/vocab/ThankYouKeyword.voc
ovos_skill_hello_world/locale/cs-cz/dialog/hello.world.dialog
ovos_skill_hello_world/locale/cs-cz/dialog/how.are.you.dialog
ovos_skill_hello_world/locale/cs-cz/dialog/welcome.dialog
ovos_skill_hello_world/locale/cs-cz/intents/HowAreYou.intent
ovos_skill_hello_world/locale/cs-cz/vocab/HelloWorldKeyword.voc
ovos_skill_hello_world/locale/cs-cz/vocab/ThankYouKeyword.voc
ovos_skill_hello_world/locale/da-dk/skill.json
ovos_skill_hello_world/locale/da-dk/dialog/hello.world.dialog
ovos_skill_hello_world/locale/da-dk/dialog/how.are.you.dialog
ovos_skill_hello_world/locale/da-dk/dialog/welcome.dialog
ovos_skill_hello_world/locale/da-dk/intents/HowAreYou.intent
ovos_skill_hello_world/locale/da-dk/vocab/HelloWorldKeyword.voc
ovos_skill_hello_world/locale/da-dk/vocab/ThankYouKeyword.voc
ovos_skill_hello_world/locale/de-de/skill.json
ovos_skill_hello_world/locale/de-de/dialog/hello.dialog
ovos_skill_hello_world/locale/de-de/dialog/hello.world.dialog
ovos_skill_hello_world/locale/de-de/dialog/how.are.you.dialog
ovos_skill_hello_world/locale/de-de/dialog/welcome.dialog
ovos_skill_hello_world/locale/de-de/intents/Greetings.intent
ovos_skill_hello_world/locale/de-de/intents/HowAreYou.intent
ovos_skill_hello_world/locale/de-de/vocab/HelloWorldKeyword.voc
ovos_skill_hello_world/ovos_skill_hello_world.egg-info/PKG-INFO
ovos_skill_hello_world/ovos_skill_hello_world.egg-info/SOURCES.txt
ovos_skill_hello_world/ovos_skill_hello_world.egg-info/dependency_links.txt
ovos_skill_hello_world/ovos_skill_hello_world.egg-info/entry_points.txt
ovos_skill_hello_world/ovos_skill_hello_world.egg-info/top_level.txt
ovos_skill_hello_world-0.2.1.dist-info/LICENSE
ovos_skill_hello_world-0.2.1.dist-info/METADATA
ovos_skill_hello_world-0.2.1.dist-info/WHEEL
ovos_skill_hello_world-0.2.1.dist-info/entry_points.txt
ovos_skill_hello_world-0.2.1.dist-info/top_level.txt
ovos_skill_hello_world-0.2.1.dist-info/RECORD
