Metadata-Version: 2.1
Name: ovos-skill-hello-world
Version: 0.2.1
Summary: OVOS hello world skill plugin
Home-page: https://github.com/OpenVoiceOS/ovos-skill-hello-world
Author: OpenVoiceOS
Author-email: jarbasai@mailfence.com
License: Apache-2.0
Keywords: ovos skill plugin
License-File: LICENSE
